setup.cfg
setup.py
PreTrainingChain/AbstractChain.py
PreTrainingChain/Example.py
PreTrainingChain/GridSearchExample.py
PreTrainingChain/MaxoutChain.py
PreTrainingChain/PreTrainingChain.py
PreTrainingChain/__init__.py
PreTrainingChain/pt_linear.py
PreTrainingChain/util.py
PreTrainingChain.egg-info/PKG-INFO
PreTrainingChain.egg-info/SOURCES.txt
PreTrainingChain.egg-info/dependency_links.txt
PreTrainingChain.egg-info/top_level.txt