Metadata-Version: 1.0
Name: PreTrainingChain
Version: 0.2.0
Summary: Scalable, configurable and Pre-training DNN using chainer
Home-page: https://github.com/fukatani/PreTrainingChain
Author: Ryosuke Fukatani
Author-email: nannyakannya@gmail.com
License: Apache License 2.0
Keywords: chainer,newral network,machine leaning
Platform: UNKNOWN
